{
    "elements":
    [
        { "type": "NumberSpinner", "Name": "Price", "caption": "Strompreis", "digits": 2},
        {
            "type": "List",
            "name": "Counters",
            "caption": "Zählerliste",
            "add": true,
            "delete": true,
            "sort": {
                "column": "Name",
                "direction": "ascending"
            },
            "columns": [
            {
                "caption": "Name",
                "name": "Name",
                "width": "auto",
                "add": ""
            }, 
            {
                "caption": "Gesamtverbrauch",
                "name": "Total",
                "width": "auto",
                "edit": {
                    "type": "SelectVariable",
                    "validVariableTypes": [2]
                },
                "add": 0
            }, 
            {
                "caption": "Monatsverbrauch",
                "name": "Monthly",
                "width": "auto",
                "edit": {
                    "type": "SelectVariable",
                    "validVariableTypes": [2]
                },
                "add": 0
            },
            {
                "caption": "Wochenverbrauch",
                "name": "Weekly",
                "width": "auto",
                "edit": {
                    "type": "SelectVariable",
                    "validVariableTypes": [2]
                },
                "add": 0
            },
            {
                "caption": "Tagesverbrauch",
                "name": "Daily",
                "width": "auto",
                "edit": {
                    "type": "SelectVariable",
                    "validVariableTypes": [2]
                },
                "add": 0
            },
            {
                "caption": "Limit",
                "name": "Limit",
                "width": "auto",
                "edit": {
                    "type": "NumberSpinner",
                    "digits": 2
                },
                "add": 0.1
            }
        
        
        ]
        }

    ],
    "actions":
    [

    ],
    "status":
    [

    ]
}